Metadata-Version: 2.1
Name: polypheny
Version: 1.0.0
Summary: Driver for Polypheny
Home-page: https://polypheny.com/
Author: The Polypheny Project
Author-email: mail@polypheny.org
License: Apache License, Version 2.0
Project-URL: Documentation, https://docs.polypheny.com/en/latest/drivers/python/overview
Project-URL: Code, https://github.com/polypheny/Polypheny-Connector-Python
Project-URL: Issue tracker, https://github.com/polypheny/Polypheny-DB/labels/A-python
Platform: UNKNOWN
Requires-Python: >=3.8
